{
  "confirmDeletion": true,
  "showAddCommand": true,
  "debug": false,
  "editorMenu": [
    {
      "id": "wikipedia-search:link-article",
      "icon": "book-open",
      "name": "Wikipedia: Link Article",
      "mode": "any"
    },
    {
      "id": "obsidian-excalidraw-plugin:excalidraw-autocreate-and-embed-popout",
      "icon": "brush",
      "name": "Create new drawing in active document",
      "mode": "any"
    }
  ],
  "fileMenu": [
    {
      "id": "obsidian-excalidraw-plugin:excalidraw-autocreate-and-embed-popout",
      "icon": "brush",
      "name": "Create new drawing in active document",
      "mode": "any"
    }
  ],
  "leftRibbon": [
    {
      "id": "obsidian-excalidraw-plugin:excalidraw-autocreate-and-embed-popout",
      "icon": "brush",
      "name": "Create new drawing in active document",
      "mode": "any"
    }
  ],
  "rightRibbon": [],
  "titleBar": [],
  "statusBar": [],
  "pageHeader": [],
  "macros": [],
  "explorer": [],
  "hide": {
    "statusbar": [],
    "leftRibbon": []
  },
  "spacing": 8,
  "advancedToolbar": {
    "rowHeight": 48,
    "rowCount": 1,
    "spacing": 0,
    "buttonWidth": 48,
    "columnLayout": false,
    "mappedIcons": [],
    "tooltips": false,
    "heightOffset": 0
  }
}